Metadata-Version: 2.0
Name: odoo8-addon-l10n-lu-ecdf
Version: 8.0.1.1.0
Summary: Generates XML eCDF annual financial reports
Home-page: http://acsone.eu
Author: Odoo Community Association (OCA), ACSONE SA/NV
Author-email: support@odoo-community.org
License: AGPL-3
Platform: UNKNOWN
Classifier: Programming Language :: Python
Classifier: Framework :: Odoo
Classifier: License :: OSI Approved :: GNU Affero General Public License v3
Requires-Python: ~=2.7
Requires-Dist: odoo (<9.0a,>=8.0a)
Requires-Dist: odoo8-addon-l10n-lu-ext
Requires-Dist: odoo8-addon-l10n-lu-mis-reports
Requires-Dist: odoo8-addon-mis-builder
